appmesh/__init__.py
appmesh/app.py
appmesh/app_output.py
appmesh/app_run.py
appmesh/appmesh_client.py
appmesh/client_http.py
appmesh/client_http_oauth.py
appmesh/client_tcp.py
appmesh/client_wss.py
appmesh/server_http.py
appmesh/server_tcp.py
appmesh/server_wss.py
appmesh/tcp_messages.py
appmesh/tcp_transport.py
appmesh/wss_transport.py
appmesh-2.1.4.dist-info/METADATA
appmesh-2.1.4.dist-info/WHEEL
appmesh-2.1.4.dist-info/top_level.txt
appmesh-2.1.4.dist-info/RECORD
