Metadata-Version: 2.4
Name: appmesh
Version: 2.1.4
Summary: Client SDK for App Mesh
Home-page: https://github.com/laoshanxi/app-mesh
Author: laoshanxi
Author-email: 178029200@qq.com
License: MIT
Keywords: appmesh AppMesh app-mesh
Classifier: Programming Language :: Python :: 3
Classifier: Programming Language :: Python :: 3.6
Classifier: Operating System :: OS Independent
Requires-Python: >=3
Requires-Dist: requests
Requires-Dist: websocket-client
Requires-Dist: msgpack
Requires-Dist: requests_toolbelt
Requires-Dist: aniso8601
Requires-Dist: PyJWT
Requires-Dist: dataclasses; python_version < "3.7"
Dynamic: author
Dynamic: author-email
Dynamic: classifier
Dynamic: description
Dynamic: description-content-type
Dynamic: home-page
Dynamic: keywords
Dynamic: license
Dynamic: requires-dist
Dynamic: requires-python
Dynamic: summary
